virtualenvwrapper/hook_loader.py
virtualenvwrapper/project.py
virtualenvwrapper/user_scripts.py
virtualenvwrapper/version.py
virtualenvwrapper-6.1.1.data/scripts/virtualenvwrapper.sh
virtualenvwrapper-6.1.1.data/scripts/virtualenvwrapper_lazy.sh
virtualenvwrapper-6.1.1.dist-info/LICENSE
virtualenvwrapper-6.1.1.dist-info/METADATA
virtualenvwrapper-6.1.1.dist-info/WHEEL
virtualenvwrapper-6.1.1.dist-info/entry_points.txt
virtualenvwrapper-6.1.1.dist-info/top_level.txt
virtualenvwrapper-6.1.1.dist-info/RECORD
