Metadata-Version: 2.1
Name: virtualenvwrapper
Version: 6.1.1
Author-email: Doug Hellmann <doug@doughellmann.com>, Jason Myers <jason@mailthemyers.com>
License: MIT
Project-URL: homepage, https://virtualenvwrapper.readthedocs.io/
Project-URL: repository, https://github.com/python-virtualenvwrapper/virtualenvwrapper
Keywords: virtualenv
Classifier: Development Status :: 5 - Production/Stable
Classifier: License :: OSI Approved :: MIT License
Classifier: Programming Language :: Python
Classifier: Programming Language :: Python :: 3
Classifier: Programming Language :: Python :: 3.8
Classifier: Programming Language :: Python :: 3.9
Classifier: Programming Language :: Python :: 3.10
Classifier: Programming Language :: Python :: 3.11
Classifier: Programming Language :: Python :: 3.12
Classifier: Intended Audience :: Developers
Classifier: Environment :: Console
Requires-Python: >=3.8
License-File: LICENSE
Requires-Dist: virtualenv
Requires-Dist: virtualenv-clone
Requires-Dist: stevedore
Provides-Extra: linter
Requires-Dist: flake8; extra == "linter"
Provides-Extra: build
Requires-Dist: build; extra == "build"
Requires-Dist: twine; extra == "build"
Requires-Dist: check-python-versions; extra == "build"
